{
  "lastUpdated": "2026-01-22T04:07:22.654Z",
  "lastUpdatedKST": "2026. 1. 22. 오후 1:07:22",
  "keyword": "식물 관리",
  "totalCount": 50,
  "displayCount": 9,
  "articles": [
    {
      "id": 1,
      "title": "5개년 나무심기 중장기 계획 마무리 집중",
      "link": "http://www.jejumaeil.net/news/articleView.html?idxno=354656",
      "thumbnail": "https://search.pstatic.net/common/?src=https%3A%2F%2Fimgnews.pstatic.net%2Fimage%2Forigin%2F5572%2F2026%2F01%2F22%2F75575.jpg&type=ofullfill208_208_dominantcolor&expire=2&refresh=true",
      "press": "제주매일2분 전",
      "date": "2026. 1. 22.",
      "description": "제주매일..."
    },
    {
      "id": 2,
      "title": "식이섬유·저당까지 챙겼다···하림, '오!늘단백' 신상 2종",
      "link": "https://www.thereport.co.kr/news/articleView.html?idxno=82749",
      "thumbnail": "https://search.pstatic.net/common/?src=https%3A%2F%2Fimgnews.pstatic.net%2Fimage%2Forigin%2F5780%2F2026%2F01%2F22%2F51009.jpg&type=ofullfill208_208_dominantcolor&expire=2&refresh=true",
      "press": "더리포트16분 전",
      "date": "2026. 1. 22.",
      "description": "더리포트..."
    },
    {
      "id": 3,
      "title": "한겨울 정원에 찾아온 봄의 신호…순천만국가정원서 '복수초' 개화",
      "link": "https://www.thefairnews.co.kr/news/articleView.html?idxno=67391",
      "thumbnail": "https://search.pstatic.net/common/?src=https%3A%2F%2Fimgnews.pstatic.net%2Fimage%2Forigin%2F5863%2F2026%2F01%2F22%2F53266.jpg&type=ofullfill208_208_dominantcolor&expire=2&refresh=true",
      "press": "더페어26분 전",
      "date": "2026. 1. 22.",
      "description": "더페어..."
    },
    {
      "id": 4,
      "title": "신품종보호 출원 1만 4천건 넘어…바이오·소재 분야까지 영역 확장",
      "link": "https://www.livesnews.com/news/article.html?no=58886",
      "thumbnail": "https://search.pstatic.net/common/?src=https%3A%2F%2Fimgnews.pstatic.net%2Fimage%2Forigin%2F5811%2F2026%2F01%2F22%2F27010.jpg&type=fface200_200&expire=2&refresh=true",
      "press": "라이브뉴스50분 전",
      "date": "2026. 1. 22.",
      "description": "라이브뉴스..."
    },
    {
      "id": 5,
      "title": "니케 스토리에 빠진 당신에게, 감상 추천 '2주 이벤트' 11선",
      "link": "https://www.gameple.co.kr/news/articleView.html?idxno=214889",
      "thumbnail": "https://search.pstatic.net/common/?src=https%3A%2F%2Fimgnews.pstatic.net%2Fimage%2Forigin%2F5577%2F2026%2F01%2F22%2F19004.jpg&type=fface200_200&expire=2&refresh=true",
      "press": "게임플1시간 전",
      "date": "2026. 1. 22.",
      "description": "게임플..."
    },
    {
      "id": 6,
      "title": "강진군 농업기술센터, 5개 장기 교육과정 본격 운영",
      "link": "http://www.newsmaker.or.kr/news/articleView.html?idxno=173518",
      "thumbnail": "https://search.pstatic.net/common/?src=https%3A%2F%2Fimgnews.pstatic.net%2Fimage%2Forigin%2F5159%2F2026%2F01%2F22%2F154935.jpg&type=fface200_200&expire=2&refresh=true",
      "press": "뉴스메이커1시간 전",
      "date": "2026. 1. 22.",
      "description": "뉴스메이커..."
    },
    {
      "id": 7,
      "title": "국립백두대간·세종수목원, 역대 최다 관람객 찾았다",
      "link": "http://www.fnnews.com/news/202601221112039694",
      "thumbnail": "https://search.pstatic.net/common/?src=https%3A%2F%2Fimgnews.pstatic.net%2Fimage%2Forigin%2F014%2F2026%2F01%2F22%2F5466715.jpg&type=fface200_200&expire=2&refresh=true",
      "press": "파이낸셜뉴스1시간 전네이버뉴스",
      "date": "2026. 1. 22.",
      "description": "파이낸셜뉴스..."
    },
    {
      "id": 8,
      "title": "뉴스 기사와 댓글로 인한 문제 발생시 24시간 센터로 접수해주세요.",
      "link": "https://help.naver.com/alias/news/news_21.naver",
      "thumbnail": "/logo.png",
      "press": "제주매일2분 전",
      "date": "2026. 1. 22.",
      "description": "제주매일..."
    },
    {
      "id": 9,
      "title": "안양시-서울대, 3월부터 안양수목원 '사전예약제'로 운영",
      "link": "http://www.suwonilbo.kr/news/articleView.html?idxno=314123",
      "thumbnail": "https://search.pstatic.net/common/?src=https%3A%2F%2Fimgnews.pstatic.net%2Fimage%2Forigin%2F5102%2F2026%2F01%2F22%2F113776.jpg&type=fface200_200&expire=2&refresh=true",
      "press": "수원일보1시간 전",
      "date": "2026. 1. 22.",
      "description": "수원일보..."
    },
    {
      "id": 10,
      "title": "하림, ‘오!늘단백 밀크초코 스트로베리바&치즈케이크바’ 2종 출시",
      "link": "https://cooknchefnews.com/news/view/1065579823482060",
      "thumbnail": "https://search.pstatic.net/common/?src=https%3A%2F%2Fimgnews.pstatic.net%2Fimage%2Forigin%2F5639%2F2026%2F01%2F22%2F23401.jpg&type=ofullfill208_208_dominantcolor&expire=2&refresh=true",
      "press": "쿡앤셰프1시간 전",
      "date": "2026. 1. 22.",
      "description": "쿡앤셰프..."
    },
    {
      "id": 11,
      "title": "'맑은국간장' 드셨다면 주의… 3-MCPD 기준치 46배 초과",
      "link": "https://www.newsclaim.co.kr/news/articleView.html?idxno=3053858",
      "thumbnail": "https://search.pstatic.net/common/?src=https%3A%2F%2Fimgnews.pstatic.net%2Fimage%2Forigin%2F5772%2F2026%2F01%2F22%2F56037.jpg&type=fface200_200&expire=2&refresh=true",
      "press": "뉴스클레임1시간 전",
      "date": "2026. 1. 22.",
      "description": "뉴스클레임..."
    },
    {
      "id": 12,
      "title": "식물성 음료, 무엇을 기준으로 골라야 할까…검은콩·아몬드·오트 영양...",
      "link": "https://www.ezyeconomy.com/news/articleView.html?idxno=230899",
      "thumbnail": "https://search.pstatic.net/common/?src=https%3A%2F%2Fimgnews.pstatic.net%2Fimage%2Forigin%2F5594%2F2026%2F01%2F22%2F71860.jpg&type=ofullfill208_208_dominantcolor&expire=2&refresh=true",
      "press": "이지경제1시간 전",
      "date": "2026. 1. 22.",
      "description": "이지경제..."
    },
    {
      "id": 13,
      "title": "삼화 '맑은국간장' 발암물질 '46배' 검출 … 회수",
      "link": "https://www.safetimes.co.kr/news/articleView.html?idxno=238642",
      "thumbnail": "https://search.pstatic.net/common/?src=https%3A%2F%2Fimgnews.pstatic.net%2Fimage%2Forigin%2F5754%2F2026%2F01%2F22%2F49628.jpg&type=fface200_200&expire=2&refresh=true",
      "press": "세이프타임즈1시간 전",
      "date": "2026. 1. 22.",
      "description": "세이프타임즈..."
    },
    {
      "id": 14,
      "title": "안양시, 안양수목원 '사전예약제' 운영... \"3월부터 예약없이 입장 불가...",
      "link": "http://www.hg-times.com/news/articleView.html?idxno=279077",
      "thumbnail": "https://search.pstatic.net/common/?src=https%3A%2F%2Fimgnews.pstatic.net%2Fimage%2Forigin%2F5290%2F2026%2F01%2F22%2F190549.jpg&type=ofullfill208_208_dominantcolor&expire=2&refresh=true",
      "press": "한강타임즈1시간 전",
      "date": "2026. 1. 22.",
      "description": "한강타임즈..."
    },
    {
      "id": 15,
      "title": "국립백두대간·세종수목원... 누적 610만 명 찾았다",
      "link": "https://www.goodmorningcc.com/news/articleView.html?idxno=439352",
      "thumbnail": "https://search.pstatic.net/common/?src=https%3A%2F%2Fimgnews.pstatic.net%2Fimage%2Forigin%2F5285%2F2026%2F01%2F22%2F187873.jpg&type=ofullfill208_208_dominantcolor&expire=2&refresh=true",
      "press": "굿모닝충청1시간 전",
      "date": "2026. 1. 22.",
      "description": "굿모닝충청..."
    },
    {
      "id": 16,
      "title": "한수정, 누적 관람객 610만 명 돌파···韓 대표 관광지 도약",
      "link": "http://amenews.kr/news/view.php?idx=65573",
      "thumbnail": "https://search.pstatic.net/common/?src=https%3A%2F%2Fimgnews.pstatic.net%2Fimage%2Forigin%2F5644%2F2026%2F01%2F22%2F28377.jpg&type=ofullfill208_208_dominantcolor&expire=2&refresh=true",
      "press": "신소재경제신문2시간 전",
      "date": "2026. 1. 22.",
      "description": "신소재경제신문..."
    },
    {
      "id": 17,
      "title": "안양시-서울대, 안양수목원 3월부터 사전예약제 전환",
      "link": "https://www.newscj.com/news/articleView.html?idxno=3366298",
      "thumbnail": "https://search.pstatic.net/common/?src=https%3A%2F%2Fimgnews.pstatic.net%2Fimage%2Forigin%2F5041%2F2026%2F01%2F22%2F1148690.jpg&type=fface200_200&expire=2&refresh=true",
      "press": "천지일보2시간 전",
      "date": "2026. 1. 22.",
      "description": "천지일보..."
    },
    {
      "id": 18,
      "title": "한국수목원정원관리원, 개원 이후 누적 관람객 610만 명 돌파",
      "link": "https://www.discoverynews.kr/news/articleView.html?idxno=1083355",
      "thumbnail": "https://search.pstatic.net/common/?src=https%3A%2F%2Fimgnews.pstatic.net%2Fimage%2Forigin%2F5613%2F2026%2F01%2F22%2F153617.jpg&type=ofullfill208_208_dominantcolor&expire=2&refresh=true",
      "press": "디스커버리뉴스2시간 전",
      "date": "2026. 1. 22.",
      "description": "디스커버리뉴스..."
    },
    {
      "id": 19,
      "title": "강진군, 디지털·문화·전문농업 인재 양성 주력",
      "link": "https://www.newspim.com/news/view/20260122000349",
      "thumbnail": "https://search.pstatic.net/common/?src=https%3A%2F%2Fimgnews.pstatic.net%2Fimage%2Forigin%2F5002%2F2026%2F01%2F22%2F3077128.jpg&type=fface200_200&expire=2&refresh=true",
      "press": "뉴스핌2시간 전",
      "date": "2026. 1. 22.",
      "description": "뉴스핌..."
    },
    {
      "id": 20,
      "title": "서귀포시, 나무심기 중장기 계획 연계 녹색도시 전환 가속",
      "link": "http://www.headlinejeju.co.kr/news/articleView.html?idxno=585495",
      "thumbnail": "https://search.pstatic.net/common/?src=https%3A%2F%2Fimgnews.pstatic.net%2Fimage%2Forigin%2F5267%2F2026%2F01%2F22%2F297952.jpg&type=ofullfill208_208_dominantcolor&expire=2&refresh=true",
      "press": "헤드라인제주2시간 전",
      "date": "2026. 1. 22.",
      "description": "헤드라인제주..."
    },
    {
      "id": 21,
      "title": "안양시-서울대, 안양수목원, 3월부터 사전 예약제 전면 시행",
      "link": "https://www.jeonmae.co.kr/news/articleView.html?idxno=1223844",
      "thumbnail": "https://search.pstatic.net/common/?src=https%3A%2F%2Fimgnews.pstatic.net%2Fimage%2Forigin%2F5844%2F2026%2F01%2F22%2F300395.jpg&type=fface200_200&expire=2&refresh=true",
      "press": "전국매일신문2시간 전",
      "date": "2026. 1. 22.",
      "description": "전국매일신문..."
    },
    {
      "id": 22,
      "title": "체코 브르디 지역에 되살아난 '기적의 숲'",
      "link": "https://www.newspenguin.com/news/articleView.html?idxno=21088",
      "thumbnail": "https://search.pstatic.net/common/?src=https%3A%2F%2Fimgnews.pstatic.net%2Fimage%2Forigin%2F5849%2F2026%2F01%2F22%2F8549.jpg&type=ofullfill208_208_dominantcolor&expire=2&refresh=true",
      "press": "뉴스펭귄2시간 전",
      "date": "2026. 1. 22.",
      "description": "뉴스펭귄..."
    },
    {
      "id": 23,
      "title": "최대호의 '진심'으로 열린 안양수목원…3월부터 사전예약제",
      "link": "https://www.nocutnews.co.kr/news/6460172?utm_source=naver&utm_medium=article&utm_campaign=20260122101309",
      "thumbnail": "https://search.pstatic.net/common/?src=https%3A%2F%2Fimgnews.pstatic.net%2Fimage%2Forigin%2F079%2F2026%2F01%2F22%2F4107797.jpg&type=fface200_200&expire=2&refresh=true",
      "press": "노컷뉴스2시간 전네이버뉴스",
      "date": "2026. 1. 22.",
      "description": "노컷뉴스..."
    },
    {
      "id": 24,
      "title": "[남해군 소식] 남해군 '코리아둘레길 쉼터 운영 우수 지자체' 선정",
      "link": "http://www.newsprime.co.kr/news/article.html?no=721218",
      "thumbnail": "https://search.pstatic.net/common/?src=https%3A%2F%2Fimgnews.pstatic.net%2Fimage%2Forigin%2F5325%2F2026%2F01%2F22%2F384807.jpg&type=fface200_200&expire=2&refresh=true",
      "press": "프라임경제2시간 전",
      "date": "2026. 1. 22.",
      "description": "프라임경제..."
    },
    {
      "id": 25,
      "title": "진주시, \"제5기 진주시민정원사 양성교육 기초과정\" 교육생 모집",
      "link": "https://www.siminilbo.co.kr/news/newsview.php?ncode=1160301935839785",
      "thumbnail": "https://search.pstatic.net/common/?src=https%3A%2F%2Fimgnews.pstatic.net%2Fimage%2Forigin%2F5055%2F2026%2F01%2F22%2F872918.jpg&type=ofullfill208_208_dominantcolor&expire=2&refresh=true",
      "press": "시민일보3시간 전",
      "date": "2026. 1. 22.",
      "description": "시민일보..."
    },
    {
      "id": 26,
      "title": "식물자원 보호와 쾌적한 탐방 환경 조성을 위해 3월 1일부터 수목원 탐방 사전 예약제를 본격 시행한다고 22일 밝혔다. 시와 서울대(총장 유홍림)는 비개방 수목원이었던 서울대 안양",
      "link": "http://www.m-i.kr/news/articleView.html?idxno=1328327",
      "thumbnail": "https://search.pstatic.net/common/?src=https%3A%2F%2Fimgnews.pstatic.net%2Fimage%2Forigin%2F5385%2F2026%2F01%2F22%2F835958.jpg&type=fface200_200&expire=2&refresh=true",
      "press": "매일일보3시간 전",
      "date": "2026. 1. 22.",
      "description": "매일일보..."
    },
    {
      "id": 27,
      "title": "하림 오!늘단백바, 출시 10개월 만에 누적 300만 개 판매…단백질 간식...",
      "link": "http://www.m-i.kr/news/articleView.html?idxno=1328306",
      "thumbnail": "https://search.pstatic.net/common/?src=https%3A%2F%2Fimgnews.pstatic.net%2Fimage%2Forigin%2F5385%2F2026%2F01%2F22%2F835946.jpg&type=fface200_200&expire=2&refresh=true",
      "press": "매일일보3시간 전",
      "date": "2026. 1. 22.",
      "description": "매일일보..."
    },
    {
      "id": 28,
      "title": "하림, '오!늘단백 밀크초코 스트로베리바&치즈케이크바' 2종 출시",
      "link": "https://www.pressman.kr/news/articleView.html?idxno=98818",
      "thumbnail": "https://search.pstatic.net/common/?src=https%3A%2F%2Fimgnews.pstatic.net%2Fimage%2Forigin%2F5681%2F2026%2F01%2F22%2F66677.jpg&type=fface200_200&expire=2&refresh=true",
      "press": "프레스맨3시간 전",
      "date": "2026. 1. 22.",
      "description": "프레스맨..."
    },
    {
      "id": 29,
      "title": "전세계에서 오직 제주에만 있는 '한라솜다리' 7개체만 남아",
      "link": "https://www.mediajeju.com/news/articleView.html?idxno=362534",
      "thumbnail": "https://search.pstatic.net/common/?src=https%3A%2F%2Fimgnews.pstatic.net%2Fimage%2Forigin%2F5522%2F2026%2F01%2F22%2F53880.jpg&type=fface200_200&expire=2&refresh=true",
      "press": "미디어제주3시간 전",
      "date": "2026. 1. 22.",
      "description": "미디어제주..."
    },
    {
      "id": 30,
      "title": "서울대 안양수목원, 3월부터 사전 예약제 본격 시행",
      "link": "http://www.ttlnews.com/news/articleView.html?idxno=3071536",
      "thumbnail": "https://search.pstatic.net/common/?src=https%3A%2F%2Fimgnews.pstatic.net%2Fimage%2Forigin%2F5643%2F2026%2F01%2F22%2F48149.jpg&type=fface200_200&expire=2&refresh=true",
      "press": "퍼블릭뉴스통신(public news-network for TTL)3시간 전",
      "date": "2026. 1. 22.",
      "description": "퍼블릭뉴스통신(public news-network for TTL)..."
    },
    {
      "id": 31,
      "title": "단백질과 식물성의 대두 단백질, ICBP(분리닭가슴살단백질) 3종의 복합 단백질이 최적의 비율로 설계돼 제품 한 개당 16g의 단백질을 손쉽게 섭취할 수 있다. 여기에 식이섬유도 ",
      "link": "https://swtvnews.com/news/newsview.php?ncode=1065572518906026",
      "thumbnail": "https://search.pstatic.net/common/?src=https%3A%2F%2Fimgnews.pstatic.net%2Fimage%2Forigin%2F5753%2F2026%2F01%2F22%2F53140.jpg&type=ofullfill208_208_dominantcolor&expire=2&refresh=true",
      "press": "SWTV3시간 전",
      "date": "2026. 1. 22.",
      "description": "SWTV..."
    },
    {
      "id": 32,
      "title": "서울대 안양수목원 3월부터 '사전예약제' 운영",
      "link": "https://www.dailian.co.kr/news/view/1601204/?sc=Naver",
      "thumbnail": "https://search.pstatic.net/common/?src=https%3A%2F%2Fimgnews.pstatic.net%2Fimage%2Forigin%2F119%2F2026%2F01%2F22%2F3051002.jpg&type=fface200_200&expire=2&refresh=true",
      "press": "데일리안3시간 전네이버뉴스",
      "date": "2026. 1. 22.",
      "description": "데일리안..."
    },
    {
      "id": 33,
      "title": "신품종보호 출원 1.4만 건 돌파… 세계 8위 종자 강국 우뚝",
      "link": "https://www.farmnmarket.com/news/article.html?no=25464",
      "thumbnail": "https://search.pstatic.net/common/?src=https%3A%2F%2Fimgnews.pstatic.net%2Fimage%2Forigin%2F5649%2F2026%2F01%2F22%2F16976.jpg&type=ofullfill208_208_dominantcolor&expire=2&refresh=true",
      "press": "팜앤마켓매거진3시간 전",
      "date": "2026. 1. 22.",
      "description": "팜앤마켓매거진..."
    },
    {
      "id": 34,
      "title": "두 제품은 동물성인 우유 단백질, 식물성의 대두 단백질, ICBP(분리닭가슴살단백질) 3종의 복합 단백질이 최적의 비율로 설계돼 제품 한 개당 16g의 풍부한 단백질을 손쉽게 채울",
      "link": "https://www.ilyoseoul.co.kr/news/articleView.html?idxno=512047",
      "thumbnail": "https://search.pstatic.net/common/?src=https%3A%2F%2Fimgnews.pstatic.net%2Fimage%2Forigin%2F5279%2F2026%2F01%2F22%2F343747.jpg&type=fface200_200&expire=2&refresh=true",
      "press": "일요서울3시간 전",
      "date": "2026. 1. 22.",
      "description": "일요서울..."
    },
    {
      "id": 35,
      "title": "머리 외상 이후의 삶, 회복은 어디까지 가능한가",
      "link": "https://www.ibabynews.com/news/articleView.html?idxno=142958",
      "thumbnail": "https://search.pstatic.net/common/?src=https%3A%2F%2Fimgnews.pstatic.net%2Fimage%2Forigin%2F5295%2F2026%2F01%2F22%2F97379.jpg&type=ofullfill208_208_dominantcolor&expire=2&refresh=true",
      "press": "베이비뉴스4시간 전",
      "date": "2026. 1. 22.",
      "description": "베이비뉴스..."
    },
    {
      "id": 36,
      "title": "하림, '오!늘단백 밀크초코 스트로베리바&치즈케이크바' 출시",
      "link": "https://www.slist.kr/news/articleView.html?idxno=710980",
      "thumbnail": "https://search.pstatic.net/common/?src=https%3A%2F%2Fimgnews.pstatic.net%2Fimage%2Forigin%2F5575%2F2026%2F01%2F22%2F630605.jpg&type=ofullfill208_208_dominantcolor&expire=2&refresh=true",
      "press": "싱글리스트4시간 전",
      "date": "2026. 1. 22.",
      "description": "싱글리스트..."
    },
    {
      "id": 37,
      "title": "겨울새 살리는 '버드 피더' 만들기, 대안 함께 찾아요",
      "link": "https://www.hapt.co.kr/news/articleView.html?idxno=167454",
      "thumbnail": "https://search.pstatic.net/common/?src=https%3A%2F%2Fimgnews.pstatic.net%2Fimage%2Forigin%2F5870%2F2026%2F01%2F22%2F10029.jpg&type=fface200_200&expire=2&refresh=true",
      "press": "한국아파트신문4시간 전",
      "date": "2026. 1. 22.",
      "description": "한국아파트신문..."
    },
    {
      "id": 38,
      "title": "[단독] ‘한라산 에델바이스’ 한라솜다리 멸종 위기… “남은 개체 7개...",
      "link": "https://www.seoul.co.kr/news/society/2026/01/22/20260122500017?wlog_tag3=naver",
      "thumbnail": "https://search.pstatic.net/common/?src=https%3A%2F%2Fimgnews.pstatic.net%2Fimage%2Forigin%2F081%2F2026%2F01%2F22%2F3610754.jpg&type=fface200_200&expire=2&refresh=true",
      "press": "서울신문4시간 전네이버뉴스",
      "date": "2026. 1. 22.",
      "description": "서울신문..."
    },
    {
      "id": 39,
      "title": "그래디언트 래디웰, '하루영양' 시리즈 론칭…신제품 2종 출시",
      "link": "http://www.bizwnews.com/news/articleView.html?idxno=122250",
      "thumbnail": "https://search.pstatic.net/common/?src=https%3A%2F%2Fimgnews.pstatic.net%2Fimage%2Forigin%2F5813%2F2026%2F01%2F22%2F91423.jpg&type=ofullfill208_208_dominantcolor&expire=2&refresh=true",
      "press": "비즈월드4시간 전",
      "date": "2026. 1. 22.",
      "description": "비즈월드..."
    },
    {
      "id": 40,
      "title": "\"사계절 식물 매력에 빠져 보실래요\"…국립백두대간수목원, 전시콘텐츠...",
      "link": "https://www.econovill.com/news/articleView.html?idxno=726578",
      "thumbnail": "https://search.pstatic.net/common/?src=https%3A%2F%2Fimgnews.pstatic.net%2Fimage%2Forigin%2F5097%2F2026%2F01%2F22%2F421593.jpg&type=ofullfill208_208_dominantcolor&expire=2&refresh=true",
      "press": "이코노믹리뷰5시간 전",
      "date": "2026. 1. 22.",
      "description": "이코노믹리뷰..."
    },
    {
      "id": 41,
      "title": "[건강 칼럼] 한 그릇의 미나리, 몸이 반응하는 이유는?",
      "link": "http://www.edaily.co.kr/news/newspath.asp?newsid=01836806645320344",
      "thumbnail": "https://search.pstatic.net/common/?src=https%3A%2F%2Fimgnews.pstatic.net%2Fimage%2Forigin%2F018%2F2026%2F01%2F22%2F6205003.jpg&type=fface200_200&expire=2&refresh=true",
      "press": "이데일리6시간 전네이버뉴스",
      "date": "2026. 1. 22.",
      "description": "이데일리..."
    },
    {
      "id": 42,
      "title": "\"좋다고 막 먹다간 장 막혀\"… 다이어터에게 인기 '이 음식' 뭐길래 [헬...",
      "link": "http://www.fnnews.com/news/202601212222513891",
      "thumbnail": "https://search.pstatic.net/common/?src=https%3A%2F%2Fimgnews.pstatic.net%2Fimage%2Forigin%2F014%2F2026%2F01%2F22%2F5466479.jpg&type=fface200_200&expire=2&refresh=true",
      "press": "파이낸셜뉴스7시간 전네이버뉴스",
      "date": "2026. 1. 22.",
      "description": "파이낸셜뉴스..."
    },
    {
      "id": 43,
      "title": "\"폐암 말기 6개월 남아\"… 고향서 40년 더 산 男, 이유가 [헬스톡]",
      "link": "http://www.fnnews.com/news/202601211930362700",
      "thumbnail": "https://search.pstatic.net/common/?src=https%3A%2F%2Fimgnews.pstatic.net%2Fimage%2Forigin%2F014%2F2026%2F01%2F22%2F5466472.jpg&type=fface200_200&expire=2&refresh=true",
      "press": "파이낸셜뉴스8시간 전네이버뉴스",
      "date": "2026. 1. 22.",
      "description": "파이낸셜뉴스..."
    },
    {
      "id": 44,
      "title": "국립백두대간수목원, 계절별 대표 식물 중심 '전시콘텐츠' 강화",
      "link": "https://www.cstimes.com/news/articleView.html?idxno=689546",
      "thumbnail": "https://search.pstatic.net/common/?src=https%3A%2F%2Fimgnews.pstatic.net%2Fimage%2Forigin%2F5174%2F2026%2F01%2F22%2F493355.jpg&type=ofullfill208_208_dominantcolor&expire=2&refresh=true",
      "press": "컨슈머타임스12시간 전",
      "date": "2026. 1. 22.",
      "description": "컨슈머타임스..."
    },
    {
      "id": 45,
      "title": "[성현주의 기업탐방] 감악산스테이 '청정DMZ 이로운 들기름', '진짜 생들...",
      "link": "https://www.fntoday.co.kr/news/articleView.html?idxno=375400",
      "thumbnail": "https://search.pstatic.net/common/?src=https%3A%2F%2Fimgnews.pstatic.net%2Fimage%2Forigin%2F5585%2F2026%2F01%2F21%2F149056.jpg&type=ofullfill208_208_dominantcolor&expire=2&refresh=true",
      "press": "파이낸스투데이15시간 전",
      "date": "2026. 1. 22.",
      "description": "파이낸스투데이..."
    },
    {
      "id": 46,
      "title": "[특집] 스마트하고 트렌디한 '울주군', 드론으로 예산·행정력 낭비 '확...",
      "link": "http://www.ujeil.com/news/articleView.html?idxno=380076",
      "thumbnail": "https://search.pstatic.net/common/?src=https%3A%2F%2Fimgnews.pstatic.net%2Fimage%2Forigin%2F5583%2F2026%2F01%2F21%2F175898.jpg&type=fface200_200&expire=2&refresh=true",
      "press": "울산제일일보15시간 전",
      "date": "2026. 1. 22.",
      "description": "울산제일일보..."
    },
    {
      "id": 47,
      "title": "신품종보호 출원 1.4만건 넘어…기후변화·바이오·소재 분야 확장",
      "link": "http://www.newskr.kr/news/articleView.html?idxno=102584",
      "thumbnail": "https://search.pstatic.net/common/?src=https%3A%2F%2Fimgnews.pstatic.net%2Fimage%2Forigin%2F5555%2F2026%2F01%2F21%2F66216.jpg&type=ofullfill208_208_dominantcolor&expire=2&refresh=true",
      "press": "한국농어촌방송15시간 전",
      "date": "2026. 1. 22.",
      "description": "한국농어촌방송..."
    },
    {
      "id": 48,
      "title": "종자 주권의 지형 바뀐다… 신품종 보호출원 1만4천 건 넘어",
      "link": "http://www.youngnong.co.kr/news/articleView.html?idxno=57074",
      "thumbnail": "https://search.pstatic.net/common/?src=https%3A%2F%2Fimgnews.pstatic.net%2Fimage%2Forigin%2F5548%2F2026%2F01%2F21%2F40290.jpg&type=ofullfill208_208_dominantcolor&expire=2&refresh=true",
      "press": "한국영농신문16시간 전",
      "date": "2026. 1. 22.",
      "description": "한국영농신문..."
    },
    {
      "id": 49,
      "title": "한국의 생태이야기/뿌리와 낙엽이 만든 보이지 않는 경계선",
      "link": "http://www.dynews.co.kr/news/articleView.html?idxno=836101",
      "thumbnail": "https://search.pstatic.net/common/?src=https%3A%2F%2Fimgnews.pstatic.net%2Fimage%2Forigin%2F5344%2F2026%2F01%2F21%2F462962.jpg&type=ofullfill208_208_dominantcolor&expire=2&refresh=true",
      "press": "동양일보16시간 전",
      "date": "2026. 1. 22.",
      "description": "동양일보..."
    },
    {
      "id": 50,
      "title": "국가도시공원 1호 도전 인천…행정 절차 연기로 '발등에 불'",
      "link": "https://www.incheonilbo.com/news/articleView.html?idxno=1315235",
      "thumbnail": "https://search.pstatic.net/common/?src=https%3A%2F%2Fimgnews.pstatic.net%2Fimage%2Forigin%2F5193%2F2026%2F01%2F21%2F619935.jpg&type=ofullfill208_208_dominantcolor&expire=2&refresh=true",
      "press": "인천일보16시간 전",
      "date": "2026. 1. 22.",
      "description": "인천일보..."
    }
  ]
}