{
  "lastUpdated": "2026-04-13T02:03:27.126Z",
  "lastUpdatedKST": "2026. 4. 13. AM 11:03:27",
  "keyword": "식물 관리",
  "totalCount": 50,
  "displayCount": 9,
  "articles": [
    {
      "id": 1,
      "title": "[칠곡 24시] 칠곡군, 전국 기초단체장 공약이행 평가 'A등급'",
      "link": "https://www.sisajournal.com/news/articleView.html?idxno=369134",
      "thumbnail": "https://search.pstatic.net/common/?src=https%3A%2F%2Fimgnews.pstatic.net%2Fimage%2Forigin%2F586%2F2026%2F04%2F13%2F126703.jpg&type=fface200_200&expire=2&refresh=true",
      "press": "시사저널3분 전네이버뉴스",
      "date": "2026. 4. 13.",
      "description": "시사저널..."
    },
    {
      "id": 2,
      "title": "필라이즈, 웰니스 브랜드 '루티니' 론칭",
      "link": "http://www.hansbiz.co.kr/news/articleView.html?idxno=832387",
      "thumbnail": "https://search.pstatic.net/common/?src=https%3A%2F%2Fimgnews.pstatic.net%2Fimage%2Forigin%2F5438%2F2026%2F04%2F13%2F442778.jpg&type=fface200_200&expire=2&refresh=true",
      "press": "한스경제4분 전",
      "date": "2026. 4. 13.",
      "description": "한스경제..."
    },
    {
      "id": 3,
      "title": "수입우유 무관세 시대… 국산우유, 프리미엄화·수출로 활로",
      "link": "http://www.youngnong.co.kr/news/articleView.html?idxno=58713",
      "thumbnail": "https://search.pstatic.net/common/?src=https%3A%2F%2Fimgnews.pstatic.net%2Fimage%2Forigin%2F5548%2F2026%2F04%2F13%2F41671.jpg&type=fface200_200&expire=2&refresh=true",
      "press": "한국영농신문10분 전",
      "date": "2026. 4. 13.",
      "description": "한국영농신문..."
    },
    {
      "id": 4,
      "title": "광해광업공단, 영월 광물찌꺼기저장시설 부지 경관 개선",
      "link": "https://weekly.hankooki.com/news/articleView.html?idxno=7159584",
      "thumbnail": "https://search.pstatic.net/common/?src=https%3A%2F%2Fimgnews.pstatic.net%2Fimage%2Forigin%2F5723%2F2026%2F04%2F13%2F50847.jpg&type=ofullfill208_208_dominantcolor&expire=2&refresh=true",
      "press": "주간한국12분 전",
      "date": "2026. 4. 13.",
      "description": "주간한국..."
    },
    {
      "id": 5,
      "title": "안민석 경기도교육감 예비후보 \"1학생 1반려식물\"…정서 안정 정책 제시",
      "link": "http://www.paxetv.com/news/articleView.html?idxno=269323",
      "thumbnail": "https://search.pstatic.net/common/?src=https%3A%2F%2Fimgnews.pstatic.net%2Fimage%2Forigin%2F5802%2F2026%2F04%2F13%2F155980.jpg&type=fface200_200&expire=2&refresh=true",
      "press": "팍스경제TV20분 전",
      "date": "2026. 4. 13.",
      "description": "팍스경제TV..."
    },
    {
      "id": 6,
      "title": "\"내가 키우면 꼭 죽는 식물…사진 한 장으로 돌봄 방법 찾는다\"",
      "link": "https://www.jnilbo.com/news/articleView.html?idxno=90000030135",
      "thumbnail": "https://search.pstatic.net/common/?src=https%3A%2F%2Fimgnews.pstatic.net%2Fimage%2Forigin%2F5379%2F2026%2F04%2F13%2F300177.jpg&type=fface200_200&expire=2&refresh=true",
      "press": "전남일보26분 전",
      "date": "2026. 4. 13.",
      "description": "전남일보..."
    },
    {
      "id": 7,
      "title": "부여군, 치매환자 위한 '펀앤팜' 원예 치유 프로그램 가동",
      "link": "http://www.chungnamilbo.co.kr/news/articleView.html?idxno=882990",
      "thumbnail": "https://search.pstatic.net/common/?src=https%3A%2F%2Fimgnews.pstatic.net%2Fimage%2Forigin%2F5347%2F2026%2F04%2F13%2F500317.jpg&type=fface200_200&expire=2&refresh=true",
      "press": "충남일보46분 전",
      "date": "2026. 4. 13.",
      "description": "충남일보..."
    },
    {
      "id": 8,
      "title": "내가 키우면 꼭 죽는 식물… \"사진 한 장으로 AI가 돌봄 방법 찾는다\"",
      "link": "https://www.aitimes.kr/news/articleView.html?idxno=39520",
      "thumbnail": "https://search.pstatic.net/common/?src=https%3A%2F%2Fimgnews.pstatic.net%2Fimage%2Forigin%2F5830%2F2026%2F04%2F13%2F20426.jpg&type=fface200_200&expire=2&refresh=true",
      "press": "인공지능신문50분 전",
      "date": "2026. 4. 13.",
      "description": "인공지능신문..."
    },
    {
      "id": 9,
      "title": "뉴스 기사와 댓글로 인한 문제 발생시 24시간 센터로 접수해주세요.",
      "link": "https://help.naver.com/alias/news/news_21.naver",
      "thumbnail": "https://search.pstatic.net/common/?src=https%3A%2F%2Fmimgnews.pstatic.net%2Fimage%2Fupload%2Foffice_logo%2F586%2F2025%2F03%2F07%2Flogo_586_100_20250307145713.png&type=f54_54&expire=24&refresh=true",
      "press": "시사저널3분 전네이버뉴스",
      "date": "2026. 4. 13.",
      "description": "시사저널..."
    },
    {
      "id": 10,
      "title": "GIST 학생팀, AI 홈가드닝 앱 실증 착수…SK인텔릭스와 협업",
      "link": "https://www.dailian.co.kr/news/view/1632666/?sc=Naver",
      "thumbnail": "https://search.pstatic.net/common/?src=https%3A%2F%2Fimgnews.pstatic.net%2Fimage%2Forigin%2F119%2F2026%2F04%2F13%2F3079813.jpg&type=fface200_200&expire=2&refresh=true",
      "press": "데일리안53분 전네이버뉴스",
      "date": "2026. 4. 13.",
      "description": "데일리안..."
    },
    {
      "id": 11,
      "title": "[종합]\"푸드루트,바르닭,생활과생각,배민국민건강보험\" 등 4월 13일 캐시...",
      "link": "http://www.economytalk.kr/news/articleView.html?idxno=420313",
      "thumbnail": "https://search.pstatic.net/common/?src=https%3A%2F%2Fimgnews.pstatic.net%2Fimage%2Forigin%2F5192%2F2026%2F04%2F13%2F128254.jpg&type=fface200_200&expire=2&refresh=true",
      "press": "이코노미톡뉴스55분 전",
      "date": "2026. 4. 13.",
      "description": "이코노미톡뉴스..."
    },
    {
      "id": 12,
      "title": "광해광업공단, 영월 상동광산 광물찌꺼기저장시설 부지에 경관개선 사업",
      "link": "https://www.pinpointnews.co.kr/news/articleView.html?idxno=444937",
      "thumbnail": "https://search.pstatic.net/common/?src=https%3A%2F%2Fimgnews.pstatic.net%2Fimage%2Forigin%2F5829%2F2026%2F04%2F13%2F406515.jpg&type=fface200_200&expire=2&refresh=true",
      "press": "핀포인트뉴스1시간 전",
      "date": "2026. 4. 13.",
      "description": "핀포인트뉴스..."
    },
    {
      "id": 13,
      "title": "인테리어베이, \"플랜테리어로 완성하는 상업 인테리어···공간 경험 경...",
      "link": "https://www.enetnews.co.kr/news/articleView.html?idxno=48768",
      "thumbnail": "https://search.pstatic.net/common/?src=https%3A%2F%2Fimgnews.pstatic.net%2Fimage%2Forigin%2F5866%2F2026%2F04%2F13%2F33387.jpg&type=fface200_200&expire=2&refresh=true",
      "press": "이넷뉴스1시간 전",
      "date": "2026. 4. 13.",
      "description": "이넷뉴스..."
    },
    {
      "id": 14,
      "title": "ADP-DERMA, '알라딘 알엑스 EP 400' 출시",
      "link": "https://www.gukjenews.com/news/articleView.html?idxno=3555381",
      "thumbnail": "https://search.pstatic.net/common/?src=https%3A%2F%2Fimgnews.pstatic.net%2Fimage%2Forigin%2F5291%2F2026%2F04%2F13%2F2495311.jpg&type=fface200_200&expire=2&refresh=true",
      "press": "국제뉴스1시간 전",
      "date": "2026. 4. 13.",
      "description": "국제뉴스..."
    },
    {
      "id": 15,
      "title": "에이디피더마, '알라딘 알엑스 EP 400 포스트 베리어 크림' 공식 출시",
      "link": "https://www.enetnews.co.kr/news/articleView.html?idxno=48791",
      "thumbnail": "https://search.pstatic.net/common/?src=https%3A%2F%2Fimgnews.pstatic.net%2Fimage%2Forigin%2F5866%2F2026%2F04%2F13%2F33384.jpg&type=fface200_200&expire=2&refresh=true",
      "press": "이넷뉴스1시간 전",
      "date": "2026. 4. 13.",
      "description": "이넷뉴스..."
    },
    {
      "id": 16,
      "title": "광해광업공단, 영월 상동광산 유휴부지 경관개선",
      "link": "http://amenews.kr/news/view.php?idx=66316",
      "thumbnail": "https://search.pstatic.net/common/?src=https%3A%2F%2Fimgnews.pstatic.net%2Fimage%2Forigin%2F5644%2F2026%2F04%2F13%2F29112.jpg&type=fface200_200&expire=2&refresh=true",
      "press": "신소재경제신문1시간 전",
      "date": "2026. 4. 13.",
      "description": "신소재경제신문..."
    },
    {
      "id": 17,
      "title": "코미르, 광물시설 유휴부지에 '경관개선' 사업 진행",
      "link": "http://www.ikld.kr/news/articleView.html?idxno=332706",
      "thumbnail": "https://search.pstatic.net/common/?src=https%3A%2F%2Fimgnews.pstatic.net%2Fimage%2Forigin%2F5338%2F2026%2F04%2F13%2F154293.jpg&type=fface200_200&expire=2&refresh=true",
      "press": "국토일보1시간 전",
      "date": "2026. 4. 13.",
      "description": "국토일보..."
    },
    {
      "id": 18,
      "title": "\"내가 키우면 꼭 죽는 식물… 사진 한 장으로 돌봄 방법 찾는다\" GIST 학...",
      "link": "https://www.veritas-a.com/news/articleView.html?idxno=605458",
      "thumbnail": "https://search.pstatic.net/common/?src=https%3A%2F%2Fimgnews.pstatic.net%2Fimage%2Forigin%2F5258%2F2026%2F04%2F13%2F392436.jpg&type=ofullfill208_208_dominantcolor&expire=2&refresh=true",
      "press": "베리타스알파2시간 전",
      "date": "2026. 4. 13.",
      "description": "베리타스알파..."
    },
    {
      "id": 19,
      "title": "GIST 학부생 창업팀, SK인텔릭스와 AI 홈가드닝 앱 실증",
      "link": "https://www.newspim.com/news/view/20260413000021",
      "thumbnail": "https://search.pstatic.net/common/?src=https%3A%2F%2Fimgnews.pstatic.net%2Fimage%2Forigin%2F5002%2F2026%2F04%2F13%2F3146701.jpg&type=fface200_200&expire=2&refresh=true",
      "press": "뉴스핌2시간 전",
      "date": "2026. 4. 13.",
      "description": "뉴스핌..."
    },
    {
      "id": 20,
      "title": "GIST 루티브팀·SK인텔릭스, AI 홈가드닝 앱 실증 테스트 착수",
      "link": "https://www.kyosu.net/news/articleView.html?idxno=203457",
      "thumbnail": "https://search.pstatic.net/common/?src=https%3A%2F%2Fimgnews.pstatic.net%2Fimage%2Forigin%2F5150%2F2026%2F04%2F13%2F115628.jpg&type=fface200_200&expire=2&refresh=true",
      "press": "교수신문2시간 전",
      "date": "2026. 4. 13.",
      "description": "교수신문..."
    },
    {
      "id": 21,
      "title": "\"사진 한 장으로 식물 상태 진단\"… GIST 학생창업팀, AI 홈가드닝 앱 실...",
      "link": "http://www.newsworker.co.kr/news/articleView.html?idxno=421650",
      "thumbnail": "https://search.pstatic.net/common/?src=https%3A%2F%2Fimgnews.pstatic.net%2Fimage%2Forigin%2F5521%2F2026%2F04%2F13%2F300028.jpg&type=fface200_200&expire=2&refresh=true",
      "press": "뉴스워커2시간 전",
      "date": "2026. 4. 13.",
      "description": "뉴스워커..."
    },
    {
      "id": 22,
      "title": "[종합]\"바르닭,생활과생각,배민,11번가,국민건강보험\" 등 4월 13일 캐시워...",
      "link": "http://www.economytalk.kr/news/articleView.html?idxno=420306",
      "thumbnail": "https://search.pstatic.net/common/?src=https%3A%2F%2Fimgnews.pstatic.net%2Fimage%2Forigin%2F5192%2F2026%2F04%2F13%2F128246.jpg&type=fface200_200&expire=2&refresh=true",
      "press": "이코노미톡뉴스3시간 전",
      "date": "2026. 4. 13.",
      "description": "이코노미톡뉴스..."
    },
    {
      "id": 23,
      "title": "[사설] 골목 가꾸기, 지속 가능한 관리가 답이다",
      "link": "https://www.cctoday.co.kr/news/articleView.html?idxno=2228464",
      "thumbnail": "https://search.pstatic.net/common/?src=https%3A%2F%2Fimgnews.pstatic.net%2Fimage%2Forigin%2F5160%2F2026%2F04%2F13%2F609133.jpg&type=ofullfill208_208_dominantcolor&expire=2&refresh=true",
      "press": "충청투데이5시간 전",
      "date": "2026. 4. 13.",
      "description": "충청투데이..."
    },
    {
      "id": 24,
      "title": "서천군, 습지보호위원회 개최 … 2027년 해양보호구역 사업 11건 11.9억 심...",
      "link": "https://www.tournews21.com/news/articleView.html?idxno=133578",
      "thumbnail": "https://search.pstatic.net/common/?src=https%3A%2F%2Fimgnews.pstatic.net%2Fimage%2Forigin%2F5675%2F2026%2F04%2F13%2F77560.jpg&type=fface200_200&expire=2&refresh=true",
      "press": "투어코리아뉴스5시간 전",
      "date": "2026. 4. 13.",
      "description": "투어코리아뉴스..."
    },
    {
      "id": 25,
      "title": "단종·정순왕후 애틋한 서사 들꽃으로 피어나다",
      "link": "https://www.kado.net/news/articleView.html?idxno=2044149",
      "thumbnail": "https://search.pstatic.net/common/?src=https%3A%2F%2Fimgnews.pstatic.net%2Fimage%2Forigin%2F654%2F2026%2F04%2F13%2F175241.jpg&type=fface200_200&expire=2&refresh=true",
      "press": "강원도민일보14면 1단10시간 전네이버뉴스",
      "date": "2026. 4. 13.",
      "description": "강원도민일보..."
    },
    {
      "id": 26,
      "title": "불교 가치 확장…반려동물 비건 펫푸드 첫 공개",
      "link": "https://www.vegannews.co.kr/news/article.html?no=382142",
      "thumbnail": "https://search.pstatic.net/common/?src=https%3A%2F%2Fimgnews.pstatic.net%2Fimage%2Forigin%2F5888%2F2026%2F04%2F12%2F22407.jpg&type=fface200_200&expire=2&refresh=true",
      "press": "비건뉴스11시간 전",
      "date": "2026. 4. 13.",
      "description": "비건뉴스..."
    },
    {
      "id": 27,
      "title": "서천군, 2026년도 습지보호위원회 개최",
      "link": "https://www.ccdailynews.com/news/articleView.html?idxno=2409466",
      "thumbnail": "https://search.pstatic.net/common/?src=https%3A%2F%2Fmimgnews.pstatic.net%2Fimage%2Fupload%2Foffice_logo%2F5116%2F2024%2F05%2F30%2Flogo_5116_18_20240530171556.png&type=f54_54&expire=24&refresh=true",
      "press": "충청일보12시간 전",
      "date": "2026. 4. 13.",
      "description": "충청일보..."
    },
    {
      "id": 28,
      "title": "음성군, 봉학골 정원 내 목조식물원 조성 본격화",
      "link": "https://www.ccdailynews.com/news/articleView.html?idxno=2409578",
      "thumbnail": "https://search.pstatic.net/common/?src=https%3A%2F%2Fimgnews.pstatic.net%2Fimage%2Forigin%2F5116%2F2026%2F04%2F12%2F1046445.jpg&type=fface200_200&expire=2&refresh=true",
      "press": "충청일보13시간 전",
      "date": "2026. 4. 13.",
      "description": "충청일보..."
    },
    {
      "id": 29,
      "title": "[종합]\"생활과생각, 바르닭,배민,11번가,국민건강보험\" 등 4월 12일 캐시...",
      "link": "http://www.economytalk.kr/news/articleView.html?idxno=420302",
      "thumbnail": "https://search.pstatic.net/common/?src=https%3A%2F%2Fimgnews.pstatic.net%2Fimage%2Forigin%2F5192%2F2026%2F04%2F12%2F128243.jpg&type=fface200_200&expire=2&refresh=true",
      "press": "이코노미톡뉴스14시간 전",
      "date": "2026. 4. 13.",
      "description": "이코노미톡뉴스..."
    },
    {
      "id": 30,
      "title": "봉학골에 들어설 '130억 목조 식물원'… 음성군, 밑그림 그리기 착수",
      "link": "https://www.ccdn.co.kr/news/articleView.html?idxno=1072818",
      "thumbnail": "https://search.pstatic.net/common/?src=https%3A%2F%2Fimgnews.pstatic.net%2Fimage%2Forigin%2F5278%2F2026%2F04%2F12%2F598088.jpg&type=fface200_200&expire=2&refresh=true",
      "press": "충청매일19시간 전",
      "date": "2026. 4. 13.",
      "description": "충청매일..."
    },
    {
      "id": 31,
      "title": "서천군, 11억 규모 해양보호 청사진 확정…세계유산 갯벌 보전 속도",
      "link": "http://www.dynews.co.kr/news/articleView.html?idxno=846183",
      "thumbnail": "https://search.pstatic.net/common/?src=https%3A%2F%2Fimgnews.pstatic.net%2Fimage%2Forigin%2F5344%2F2026%2F04%2F12%2F472858.jpg&type=fface200_200&expire=2&refresh=true",
      "press": "동양일보19시간 전",
      "date": "2026. 4. 13.",
      "description": "동양일보..."
    },
    {
      "id": 32,
      "title": "일찍 만개한 벚꽃이 전하는 의미",
      "link": "https://www.kihoilbo.co.kr/news/articleView.html?idxno=3019309",
      "thumbnail": "https://search.pstatic.net/common/?src=https%3A%2F%2Fimgnews.pstatic.net%2Fimage%2Forigin%2F5154%2F2026%2F04%2F12%2F589884.jpg&type=ofullfill208_208_dominantcolor&expire=2&refresh=true",
      "press": "기호일보20시간 전",
      "date": "2026. 4. 13.",
      "description": "기호일보..."
    },
    {
      "id": 33,
      "title": "음성군 봉학골 정원 내 목조식물원 조성",
      "link": "http://www.cctimes.kr/news/articleView.html?idxno=901344",
      "thumbnail": "https://search.pstatic.net/common/?src=https%3A%2F%2Fimgnews.pstatic.net%2Fimage%2Forigin%2F5498%2F2026%2F04%2F12%2F374770.jpg&type=fface200_200&expire=2&refresh=true",
      "press": "충청타임즈21시간 전",
      "date": "2026. 4. 13.",
      "description": "충청타임즈..."
    },
    {
      "id": 34,
      "title": "특히 선도리 갯벌 복원사업은 노둣길 철거를 완료하고 모래갯벌 복원 및 염생식물 식재 등 마무리 단계에 있으며, 서천갯벌 방문자센터는 현재 공정률 46%로 올해 11월 준공을 목표로",
      "link": "http://www.cctimes.kr/news/articleView.html?idxno=901338",
      "thumbnail": "https://search.pstatic.net/common/?src=https%3A%2F%2Fimgnews.pstatic.net%2Fimage%2Forigin%2F5498%2F2026%2F04%2F12%2F374776.jpg&type=fface200_200&expire=2&refresh=true",
      "press": "충청타임즈21시간 전",
      "date": "2026. 4. 13.",
      "description": "충청타임즈..."
    },
    {
      "id": 35,
      "title": "\"화잘먹 세안제 시대 열린다\"... 다기능 클렌징 시대 개막 [최기자의 화...",
      "link": "https://www.meconomynews.com/news/articleView.html?idxno=130094",
      "thumbnail": "https://search.pstatic.net/common/?src=https%3A%2F%2Fimgnews.pstatic.net%2Fimage%2Forigin%2F5528%2F2026%2F04%2F12%2F94092.jpg&type=fface200_200&expire=2&refresh=true",
      "press": "시장경제신문22시간 전",
      "date": "2026. 4. 13.",
      "description": "시장경제신문..."
    },
    {
      "id": 36,
      "title": "서울식물원, 조경‧원예‧식물관리 '정원 식재 디자인전문가 양성과정...",
      "link": "https://www.lecturernews.com/news/articleView.html?idxno=200356",
      "thumbnail": "https://search.pstatic.net/common/?src=https%3A%2F%2Fimgnews.pstatic.net%2Fimage%2Forigin%2F5566%2F2026%2F04%2F12%2F163839.jpg&type=fface200_200&expire=2&refresh=true",
      "press": "한국강사신문22시간 전",
      "date": "2026. 4. 13.",
      "description": "한국강사신문..."
    },
    {
      "id": 37,
      "title": "남해 가볼 만한 곳, 역사와 자연이 어우러진 바다 공원의 이야기",
      "link": "https://www.joongangenews.com/news/articleView.html?idxno=509756",
      "thumbnail": "https://search.pstatic.net/common/?src=https%3A%2F%2Fimgnews.pstatic.net%2Fimage%2Forigin%2F5567%2F2026%2F04%2F12%2F175598.jpg&type=ofullfill208_208_dominantcolor&expire=2&refresh=true",
      "press": "중앙이코노미뉴스23시간 전",
      "date": "2026. 4. 13.",
      "description": "중앙이코노미뉴스..."
    },
    {
      "id": 38,
      "title": "서천군, 갯벌 등 해양보호구역 관리 약 12억 투입",
      "link": "https://www.ggilbo.com/news/articleView.html?idxno=1152096",
      "thumbnail": "https://search.pstatic.net/common/?src=https%3A%2F%2Fimgnews.pstatic.net%2Fimage%2Forigin%2F5356%2F2026%2F04%2F12%2F787562.jpg&type=fface200_200&expire=2&refresh=true",
      "press": "금강일보23시간 전",
      "date": "2026. 4. 13.",
      "description": "금강일보..."
    },
    {
      "id": 39,
      "title": "음성군, 봉학골 정원 내 목조 식물원 조성 본격화",
      "link": "https://www.ggilbo.com/news/articleView.html?idxno=1152139",
      "thumbnail": "https://search.pstatic.net/common/?src=https%3A%2F%2Fimgnews.pstatic.net%2Fimage%2Forigin%2F5356%2F2026%2F04%2F12%2F787501.jpg&type=fface200_200&expire=2&refresh=true",
      "press": "금강일보1일 전",
      "date": "2026. 4. 13.",
      "description": "금강일보..."
    },
    {
      "id": 40,
      "title": "장흥 가볼 만한 곳, 숲과 물길이 어우러진 자연의 휴식",
      "link": "https://www.joongangenews.com/news/articleView.html?idxno=509741",
      "thumbnail": "https://search.pstatic.net/common/?src=https%3A%2F%2Fimgnews.pstatic.net%2Fimage%2Forigin%2F5567%2F2026%2F04%2F12%2F175575.jpg&type=ofullfill208_208_dominantcolor&expire=2&refresh=true",
      "press": "중앙이코노미뉴스1일 전",
      "date": "2026. 4. 13.",
      "description": "중앙이코노미뉴스..."
    },
    {
      "id": 41,
      "title": "[정부 주요 일정] 경제·사회부처 주간 일정 (3월 13일 ~ 3월 17일)",
      "link": "https://www.etoday.co.kr/news/view/2574889",
      "thumbnail": "https://search.pstatic.net/common/?src=https%3A%2F%2Fimgnews.pstatic.net%2Fimage%2Forigin%2F5003%2F2026%2F04%2F12%2F2160915.jpg&type=ofullfill208_208_dominantcolor&expire=2&refresh=true",
      "press": "이투데이1일 전",
      "date": "2026. 4. 13.",
      "description": "이투데이..."
    },
    {
      "id": 42,
      "title": "인플라메이징, 조용한 염증이 노화 질환을 유발한다",
      "link": "https://www.sisajournal.com/news/articleView.html?idxno=368618",
      "thumbnail": "https://search.pstatic.net/common/?src=https%3A%2F%2Fimgnews.pstatic.net%2Fimage%2Forigin%2F586%2F2026%2F04%2F12%2F126657.jpg&type=fface200_200&expire=2&refresh=true",
      "press": "시사저널1일 전네이버뉴스",
      "date": "2026. 4. 13.",
      "description": "시사저널..."
    },
    {
      "id": 43,
      "title": "[정구성의 건강칼럼] \"작은 씨앗, 큰 변화\"…아마씨, 혈관·여성·장 건...",
      "link": "http://www.newstnt.com/news/articleView.html?idxno=606342",
      "thumbnail": "https://search.pstatic.net/common/?src=https%3A%2F%2Fimgnews.pstatic.net%2Fimage%2Forigin%2F5788%2F2026%2F04%2F12%2F203451.jpg&type=ofullfill208_208_dominantcolor&expire=2&refresh=true",
      "press": "뉴스티앤티1일 전",
      "date": "2026. 4. 13.",
      "description": "뉴스티앤티..."
    },
    {
      "id": 44,
      "title": "돈도 지침도 없다…빛바랜 벽화 수두룩 [유통기한 지난 벽화, 방치된 골...",
      "link": "https://www.cctoday.co.kr/news/articleView.html?idxno=2228426",
      "thumbnail": "https://search.pstatic.net/common/?src=https%3A%2F%2Fimgnews.pstatic.net%2Fimage%2Forigin%2F5160%2F2026%2F04%2F12%2F609113.jpg&type=fface200_200&expire=2&refresh=true",
      "press": "충청투데이1일 전",
      "date": "2026. 4. 13.",
      "description": "충청투데이..."
    },
    {
      "id": 45,
      "title": "\"보살피는게 더 중요한데\"…균열 ·오염 뒤덮여 흉물된 벽화거리",
      "link": "https://www.cctoday.co.kr/news/articleView.html?idxno=2228427",
      "thumbnail": "https://search.pstatic.net/common/?src=https%3A%2F%2Fimgnews.pstatic.net%2Fimage%2Forigin%2F5160%2F2026%2F04%2F12%2F609114.jpg&type=fface200_200&expire=2&refresh=true",
      "press": "충청투데이1일 전",
      "date": "2026. 4. 13.",
      "description": "충청투데이..."
    },
    {
      "id": 46,
      "title": "이제는 '지속 가능한 골목' 가꿀 때…리뉴얼 지속돼야",
      "link": "https://www.cctoday.co.kr/news/articleView.html?idxno=2228429",
      "thumbnail": "https://search.pstatic.net/common/?src=https%3A%2F%2Fimgnews.pstatic.net%2Fimage%2Forigin%2F5160%2F2026%2F04%2F12%2F609116.jpg&type=fface200_200&expire=2&refresh=true",
      "press": "충청투데이1일 전",
      "date": "2026. 4. 13.",
      "description": "충청투데이..."
    },
    {
      "id": 47,
      "title": "‘11㎏ 감량’ 신봉선 “다이어트 성수기” 돌입…간식 당길 땐 ‘이것...",
      "link": "https://www.seoul.co.kr/news/life/health-news/2026/04/09/20260409500240?wlog_tag3=naver",
      "thumbnail": "https://search.pstatic.net/common/?src=https%3A%2F%2Fimgnews.pstatic.net%2Fimage%2Forigin%2F081%2F2026%2F04%2F12%2F3634415.jpg&type=fface200_200&expire=2&refresh=true",
      "press": "서울신문1일 전네이버뉴스",
      "date": "2026. 4. 13.",
      "description": "서울신문..."
    },
    {
      "id": 48,
      "title": "[우리 동네 사람들] ‘구의 정원’ 김윤구 테라리움 작가",
      "link": "https://www.naeil.com/news/read/584877?ref=naver",
      "thumbnail": "https://search.pstatic.net/common/?src=https%3A%2F%2Fimgnews.pstatic.net%2Fimage%2Forigin%2F5312%2F2026%2F04%2F11%2F330808.jpg&type=ofullfill208_208_dominantcolor&expire=2&refresh=true",
      "press": "내일신문2일 전",
      "date": "2026. 4. 13.",
      "description": "내일신문..."
    },
    {
      "id": 49,
      "title": "새로움 봄, 배움과 즐거움으로 나를 업그레이드 할 시간!",
      "link": "https://www.naeil.com/news/read/584876?ref=naver",
      "thumbnail": "https://search.pstatic.net/common/?src=https%3A%2F%2Fimgnews.pstatic.net%2Fimage%2Forigin%2F5312%2F2026%2F04%2F11%2F330807.jpg&type=ofullfill208_208_dominantcolor&expire=2&refresh=true",
      "press": "내일신문2일 전",
      "date": "2026. 4. 13.",
      "description": "내일신문..."
    },
    {
      "id": 50,
      "title": "영주시, 과수화상병 선제 대응... 개화기 3회 방제 강화",
      "link": "https://www.kbsm.net/news/view.php?idx=515414",
      "thumbnail": "https://search.pstatic.net/common/?src=https%3A%2F%2Fimgnews.pstatic.net%2Fimage%2Forigin%2F5533%2F2026%2F04%2F11%2F330948.jpg&type=ofullfill208_208_dominantcolor&expire=2&refresh=true",
      "press": "경북신문2일 전",
      "date": "2026. 4. 13.",
      "description": "경북신문..."
    }
  ]
}